{"scope.version":"2","timeline.animationMode":"proMode","viewport.width":300,"viewport.height":600,"design.userpaddingleft":-420,"design.userpaddingtop":-600,"design.scrollleft":103,"design.scrolltop":603,"library.openDirectories":[],"library.GroupsPath":{},"library.downloadedAssets":{},"design.zoom":1,"timeline.zoomLevel":75,"tool.text.optionsState":{"fontName":"Poppins","fontSize":"16px","fontWeight":"normal","fontStyle":"normal","alignLeft":true,"alignCenter":false,"alignRight":false,"alignJustify":false,"verticalAlignCenter":false,"foreColor":"rgb(0, 0, 0)","tagName":"p","orderedList":false,"unorderedList":false}}